{
  "ts": "2026-05-04T19:08:40.610205+09:00",
  "start_date": "2026-03-01",
  "status": "running",
  "equity": 26175.58,
  "available": 18949.87,
  "unrealized": -512.27,
  "daily_pnl": -153.01,
  "total_pnl": 5175.58,
  "cum_pct": 24.65,
  "daily_avg_pct": 0.3396,
  "annual_pct": 244.68,
  "mdd": -8.02,
  "current_dd": -5.17,
  "seed_used": 7225.71,
  "seed_used_pct": 27.6,
  "long_count": 8,
  "short_count": 6,
  "positions": [
    {
      "symbol": "ONDOUSDT",
      "side": "SHORT",
      "pnl": -548.05,
      "pnl_pct": -3.48,
      "margin": 2330.04,
      "leverage": "7",
      "tier": "10/11",
      "entry": 0.2921,
      "mark": 0.3023
    },
    {
      "symbol": "BCHUSDT",
      "side": "LONG",
      "pnl": -72.44,
      "pnl_pct": -1.66,
      "margin": 429.67,
      "leverage": "10",
      "tier": "3/9",
      "entry": 445.8322,
      "mark": 438.44
    },
    {
      "symbol": "DOTUSDT",
      "side": "SHORT",
      "pnl": 40.18,
      "pnl_pct": 1.88,
      "margin": 420.22,
      "leverage": "5",
      "tier": "7/9",
      "entry": 1.238,
      "mark": 1.2148
    },
    {
      "symbol": "ADAUSDT",
      "side": "SHORT",
      "pnl": 54.78,
      "pnl_pct": 1.65,
      "margin": 408.94,
      "leverage": "8",
      "tier": "4/9",
      "entry": 0.2527,
      "mark": 0.2485
    },
    {
      "symbol": "SOLUSDT",
      "side": "SHORT",
      "pnl": 41.88,
      "pnl_pct": 1.58,
      "margin": 373.37,
      "leverage": "7",
      "tier": "4/9",
      "entry": 85.1123,
      "mark": 83.77
    },
    {
      "symbol": "WLFIUSDT",
      "side": "SHORT",
      "pnl": -2.99,
      "pnl_pct": -0.19,
      "margin": 260.17,
      "leverage": "6",
      "tier": "4/10",
      "entry": 0.0596,
      "mark": 0.0597
    },
    {
      "symbol": "ARBUSDT",
      "side": "LONG",
      "pnl": -16.57,
      "pnl_pct": -1.31,
      "margin": 208.54,
      "leverage": "6",
      "tier": "3/10",
      "entry": 0.1161,
      "mark": 0.1146
    },
    {
      "symbol": "PENGUUSDT",
      "side": "LONG",
      "pnl": -15.66,
      "pnl_pct": -1.47,
      "margin": 130.98,
      "leverage": "8",
      "tier": "2/11",
      "entry": 0.01,
      "mark": 0.0099
    },
    {
      "symbol": "APTUSDT",
      "side": "SHORT",
      "pnl": 17.77,
      "pnl_pct": 2.94,
      "margin": 117.39,
      "leverage": "5",
      "tier": "4/9",
      "entry": 0.9992,
      "mark": 0.9698
    },
    {
      "symbol": "TAOUSDT",
      "side": "LONG",
      "pnl": 3.43,
      "pnl_pct": 0.4,
      "margin": 107.89,
      "leverage": "8",
      "tier": "1/9",
      "entry": 286.6556,
      "mark": 287.8
    },
    {
      "symbol": "AVAXUSDT",
      "side": "LONG",
      "pnl": 3.22,
      "pnl_pct": 0.64,
      "margin": 63.05,
      "leverage": "8",
      "tier": "3/9",
      "entry": 9.031,
      "mark": 9.089
    },
    {
      "symbol": "LINKUSDT",
      "side": "LONG",
      "pnl": 2.31,
      "pnl_pct": 0.54,
      "margin": 53.83,
      "leverage": "8",
      "tier": "2/9",
      "entry": 9.272,
      "mark": 9.322
    },
    {
      "symbol": "XRPUSDT",
      "side": "LONG",
      "pnl": -11.13,
      "pnl_pct": -3.24,
      "margin": 41.6,
      "leverage": "8",
      "tier": "1/9",
      "entry": 1.4404,
      "mark": 1.3938
    },
    {
      "symbol": "NEARUSDT",
      "side": "LONG",
      "pnl": -9.12,
      "pnl_pct": -2.14,
      "margin": 27.78,
      "leverage": "15",
      "tier": "1/12",
      "entry": 1.2843,
      "mark": 1.2568
    }
  ],
  "signals": {
    "BTCUSDT": {
      "dir": "short",
      "conf": 0.504
    },
    "ETHUSDT": {
      "dir": "short",
      "conf": 0.538
    },
    "LINKUSDT": {
      "dir": "short",
      "conf": 0.517
    },
    "ADAUSDT": {
      "dir": "short",
      "conf": 0.644
    },
    "HYPEUSDT": {
      "dir": "long",
      "conf": 0.502
    },
    "1000PEPEUSDT": {
      "dir": "short",
      "conf": 0.514
    },
    "SOLUSDT": {
      "dir": "short",
      "conf": 0.702
    },
    "SUIUSDT": {
      "dir": "short",
      "conf": 0.543
    },
    "XRPUSDT": {
      "dir": "long",
      "conf": 0.511
    },
    "TAOUSDT": {
      "dir": "long",
      "conf": 0.574
    },
    "DOGEUSDT": {
      "dir": "short",
      "conf": 0.524
    },
    "HBARUSDT": {
      "dir": "short",
      "conf": 0.758
    },
    "AAVEUSDT": {
      "dir": "short",
      "conf": 0.52
    },
    "DOTUSDT": {
      "dir": "short",
      "conf": 0.577
    },
    "AVAXUSDT": {
      "dir": "long",
      "conf": 0.576
    },
    "BNBUSDT": {
      "dir": "short",
      "conf": 0.532
    },
    "TRXUSDT": {
      "dir": "short",
      "conf": 0.596
    },
    "NEARUSDT": {
      "dir": "short",
      "conf": 0.52
    },
    "ENAUSDT": {
      "dir": "short",
      "conf": 0.522
    },
    "STABLEUSDT": {
      "dir": "short",
      "conf": 0.592
    },
    "UNIUSDT": {
      "dir": "short",
      "conf": 0.596
    },
    "LTCUSDT": {
      "dir": "short",
      "conf": 0.508
    },
    "ZECUSDT": {
      "dir": "short",
      "conf": 0.531
    },
    "ARBUSDT": {
      "dir": "long",
      "conf": 0.691
    },
    "ALGOUSDT": {
      "dir": "short",
      "conf": 0.529
    },
    "TRUMPUSDT": {
      "dir": "short",
      "conf": 0.549
    },
    "WLDUSDT": {
      "dir": "short",
      "conf": 0.511
    },
    "BCHUSDT": {
      "dir": "short",
      "conf": 0.759
    },
    "XMRUSDT": {
      "dir": "long",
      "conf": 0.626
    },
    "TONUSDT": {
      "dir": "short",
      "conf": 0.52
    },
    "WLFIUSDT": {
      "dir": "short",
      "conf": 0.546
    },
    "DASHUSDT": {
      "dir": "long",
      "conf": 0.546
    },
    "RAVEUSDT": {
      "dir": "long",
      "conf": 0.758
    },
    "ASTERUSDT": {
      "dir": "short",
      "conf": 0.566
    },
    "SIRENUSDT": {
      "dir": "short",
      "conf": 0.563
    },
    "1000BONKUSDT": {
      "dir": "short",
      "conf": 0.529
    },
    "APTUSDT": {
      "dir": "short",
      "conf": 0.727
    },
    "MUSDT": {
      "dir": "short",
      "conf": 0.543
    },
    "MNTUSDT": {
      "dir": "long",
      "conf": 0.504
    },
    "PENGUUSDT": {
      "dir": "long",
      "conf": 0.638
    },
    "ONDOUSDT": {
      "dir": "long",
      "conf": 0.544
    }
  },
  "equity_hist": [
    {
      "t": "2026-04-14",
      "v": 5440.0
    },
    {
      "t": "2026-04-15",
      "v": 5409.42
    },
    {
      "t": "2026-04-16",
      "v": 5894.6
    },
    {
      "t": "2026-04-17",
      "v": 6570.21
    },
    {
      "t": "2026-04-18",
      "v": 6388.3
    },
    {
      "t": "2026-04-19",
      "v": 6256.89
    },
    {
      "t": "2026-04-20",
      "v": 5802.63
    },
    {
      "t": "2026-04-21",
      "v": 6036.57
    },
    {
      "t": "2026-04-22",
      "v": 6135.67
    },
    {
      "t": "2026-04-23",
      "v": 6157.57
    },
    {
      "t": "2026-04-24",
      "v": 7293.15
    },
    {
      "t": "2026-04-25",
      "v": 4328.2
    },
    {
      "t": "2026-04-26",
      "v": 4572.75
    },
    {
      "t": "2026-04-27",
      "v": 5182.45
    },
    {
      "t": "2026-04-28",
      "v": 5043.89
    },
    {
      "t": "2026-04-29",
      "v": 5406.93
    },
    {
      "t": "2026-04-30",
      "v": 5757.17
    },
    {
      "t": "2026-05-01",
      "v": 5842.05
    },
    {
      "t": "2026-05-02",
      "v": 5840.87
    },
    {
      "t": "2026-05-03",
      "v": 5733.36
    },
    {
      "t": "2026-05-04",
      "v": 5175.58
    }
  ],
  "trade_history": [
    {
      "ts": "2026-05-04 19:07",
      "symbol": "APTUSDT",
      "side": "Sell",
      "pnl": 17.96,
      "reason": "-"
    },
    {
      "ts": "2026-05-04 19:06",
      "symbol": "DOTUSDT",
      "side": "Sell",
      "pnl": 31.45,
      "reason": "-"
    },
    {
      "ts": "2026-05-04 18:39",
      "symbol": "LINKUSDT",
      "side": "Buy",
      "pnl": 12.63,
      "reason": "-"
    },
    {
      "ts": "2026-05-04 17:42",
      "symbol": "MUSDT",
      "side": "Buy",
      "pnl": -149.13,
      "reason": "-"
    },
    {
      "ts": "2026-05-04 15:35",
      "symbol": "DOGEUSDT",
      "side": "Buy",
      "pnl": 8.13,
      "reason": "4/12"
    },
    {
      "ts": "2026-05-04 15:35",
      "symbol": "PENGUUSDT",
      "side": "Buy",
      "pnl": -23.31,
      "reason": "4/12"
    },
    {
      "ts": "2026-05-04 15:32",
      "symbol": "TAOUSDT",
      "side": "Buy",
      "pnl": -0.85,
      "reason": "L4"
    },
    {
      "ts": "2026-05-04 13:37",
      "symbol": "ARBUSDT",
      "side": "Buy",
      "pnl": 15.65,
      "reason": "-"
    },
    {
      "ts": "2026-05-04 12:14",
      "symbol": "AVAXUSDT",
      "side": "Buy",
      "pnl": 15.72,
      "reason": "-"
    },
    {
      "ts": "2026-05-04 11:51",
      "symbol": "AVAXUSDT",
      "side": "Buy",
      "pnl": 29.57,
      "reason": "-"
    },
    {
      "ts": "2026-05-04 11:26",
      "symbol": "BCHUSDT",
      "side": "Sell",
      "pnl": 0.05,
      "reason": "L9"
    },
    {
      "ts": "2026-05-04 11:20",
      "symbol": "BCHUSDT",
      "side": "Sell",
      "pnl": 7.87,
      "reason": "2/9"
    },
    {
      "ts": "2026-05-04 11:05",
      "symbol": "PENGUUSDT",
      "side": "Buy",
      "pnl": 21.5,
      "reason": "2/10"
    },
    {
      "ts": "2026-05-04 10:34",
      "symbol": "WLDUSDT",
      "side": "Sell",
      "pnl": -0.0,
      "reason": "마진 0.0USDT < 15"
    },
    {
      "ts": "2026-05-04 10:31",
      "symbol": "WLDUSDT",
      "side": "Sell",
      "pnl": -1.6,
      "reason": "3/9"
    },
    {
      "ts": "2026-05-04 10:31",
      "symbol": "DOGEUSDT",
      "side": "Buy",
      "pnl": 7.85,
      "reason": "3/9"
    },
    {
      "ts": "2026-05-04 10:30",
      "symbol": "DOGEUSDT",
      "side": "Buy",
      "pnl": 14.96,
      "reason": "3/9"
    },
    {
      "ts": "2026-05-04 09:57",
      "symbol": "ZECUSDT",
      "side": "Sell",
      "pnl": -234.54,
      "reason": "-"
    },
    {
      "ts": "2026-05-04 09:44",
      "symbol": "TAOUSDT",
      "side": "Buy",
      "pnl": -4.74,
      "reason": "3/10"
    },
    {
      "ts": "2026-05-04 09:44",
      "symbol": "LINKUSDT",
      "side": "Sell",
      "pnl": 13.09,
      "reason": "3/10"
    }
  ],
  "num_days": 65
}