{
  "ts": "2026-04-29T12:23:49.774962+09:00",
  "start_date": "2026-03-01",
  "status": "running",
  "equity": 27215.1,
  "available": 22774.58,
  "unrealized": -151.35,
  "daily_pnl": 236.48,
  "total_pnl": 5215.1,
  "cum_pct": 23.71,
  "daily_avg_pct": 0.3552,
  "annual_pct": 264.8,
  "mdd": -8.02,
  "current_dd": -0.33,
  "seed_used": 4440.52,
  "seed_used_pct": 16.32,
  "long_count": 5,
  "short_count": 8,
  "positions": [
    {
      "symbol": "TRXUSDT",
      "side": "LONG",
      "pnl": -99.5,
      "pnl_pct": -1.25,
      "margin": 985.24,
      "leverage": "8",
      "tier": "5/9",
      "entry": 0.3259,
      "mark": 0.3218
    },
    {
      "symbol": "AAVEUSDT",
      "side": "SHORT",
      "pnl": 15.8,
      "pnl_pct": 0.79,
      "margin": 330.73,
      "leverage": "6",
      "tier": "5/11",
      "entry": 97.3791,
      "mark": 96.61
    },
    {
      "symbol": "PENGUUSDT",
      "side": "LONG",
      "pnl": -8.42,
      "pnl_pct": -0.33,
      "margin": 314.69,
      "leverage": "8",
      "tier": "5/11",
      "entry": 0.01,
      "mark": 0.01
    },
    {
      "symbol": "ZECUSDT",
      "side": "LONG",
      "pnl": -26.23,
      "pnl_pct": -1.31,
      "margin": 282.53,
      "leverage": "7",
      "tier": "1/9",
      "entry": 340.2229,
      "mark": 335.77
    },
    {
      "symbol": "BCHUSDT",
      "side": "SHORT",
      "pnl": -2.78,
      "pnl_pct": -0.13,
      "margin": 258.27,
      "leverage": "8",
      "tier": "2/9",
      "entry": 453.489,
      "mark": 454.1
    },
    {
      "symbol": "TAOUSDT",
      "side": "SHORT",
      "pnl": -12.34,
      "pnl_pct": -0.88,
      "margin": 236.66,
      "leverage": "6",
      "tier": "3/10",
      "entry": 261.0616,
      "mark": 263.35
    },
    {
      "symbol": "XMRUSDT",
      "side": "LONG",
      "pnl": 17.03,
      "pnl_pct": 0.82,
      "margin": 233.77,
      "leverage": "9",
      "tier": "3/9",
      "entry": 378.7497,
      "mark": 381.84
    },
    {
      "symbol": "DOGEUSDT",
      "side": "SHORT",
      "pnl": -7.47,
      "pnl_pct": -0.48,
      "margin": 223.47,
      "leverage": "7",
      "tier": "3/9",
      "entry": 0.1001,
      "mark": 0.1006
    },
    {
      "symbol": "AVAXUSDT",
      "side": "SHORT",
      "pnl": 5.13,
      "pnl_pct": 0.33,
      "margin": 196.25,
      "leverage": "8",
      "tier": "3/9",
      "entry": 9.2602,
      "mark": 9.23
    },
    {
      "symbol": "DOTUSDT",
      "side": "SHORT",
      "pnl": -2.96,
      "pnl_pct": -0.49,
      "margin": 87.11,
      "leverage": "7",
      "tier": "2/9",
      "entry": 1.2291,
      "mark": 1.2351
    },
    {
      "symbol": "XRPUSDT",
      "side": "LONG",
      "pnl": -26.44,
      "pnl_pct": -3.85,
      "margin": 82.62,
      "leverage": "8",
      "tier": "1/9",
      "entry": 1.4404,
      "mark": 1.385
    },
    {
      "symbol": "ARBUSDT",
      "side": "SHORT",
      "pnl": -3.45,
      "pnl_pct": -1.29,
      "margin": 38.64,
      "leverage": "7",
      "tier": "1/9",
      "entry": 0.1238,
      "mark": 0.1254
    },
    {
      "symbol": "SOLUSDT",
      "side": "SHORT",
      "pnl": 0.27,
      "pnl_pct": 3.09,
      "margin": 0.7,
      "leverage": "12",
      "tier": "1/9",
      "entry": 87.2358,
      "mark": 84.54
    }
  ],
  "signals": {
    "BTCUSDT": {
      "dir": "short",
      "conf": 0.506
    },
    "ETHUSDT": {
      "dir": "short",
      "conf": 0.501
    },
    "LINKUSDT": {
      "dir": "short",
      "conf": 0.527
    },
    "ADAUSDT": {
      "dir": "short",
      "conf": 0.658
    },
    "HYPEUSDT": {
      "dir": "long",
      "conf": 0.52
    },
    "1000PEPEUSDT": {
      "dir": "short",
      "conf": 0.517
    },
    "SOLUSDT": {
      "dir": "short",
      "conf": 0.963
    },
    "SUIUSDT": {
      "dir": "short",
      "conf": 0.937
    },
    "XRPUSDT": {
      "dir": "short",
      "conf": 0.589
    },
    "TAOUSDT": {
      "dir": "short",
      "conf": 0.59
    },
    "DOGEUSDT": {
      "dir": "short",
      "conf": 0.813
    },
    "HBARUSDT": {
      "dir": "short",
      "conf": 0.758
    },
    "AAVEUSDT": {
      "dir": "short",
      "conf": 0.51
    },
    "DOTUSDT": {
      "dir": "short",
      "conf": 0.689
    },
    "AVAXUSDT": {
      "dir": "short",
      "conf": 0.529
    },
    "BNBUSDT": {
      "dir": "long",
      "conf": 0.507
    },
    "TRXUSDT": {
      "dir": "short",
      "conf": 0.609
    },
    "NEARUSDT": {
      "dir": "short",
      "conf": 0.506
    },
    "ENAUSDT": {
      "dir": "short",
      "conf": 0.507
    },
    "STABLEUSDT": {
      "dir": "short",
      "conf": 0.592
    },
    "UNIUSDT": {
      "dir": "short",
      "conf": 0.596
    },
    "LTCUSDT": {
      "dir": "short",
      "conf": 0.508
    },
    "ZECUSDT": {
      "dir": "short",
      "conf": 0.528
    },
    "ARBUSDT": {
      "dir": "long",
      "conf": 0.602
    },
    "ALGOUSDT": {
      "dir": "short",
      "conf": 0.529
    },
    "TRUMPUSDT": {
      "dir": "short",
      "conf": 0.549
    },
    "WLDUSDT": {
      "dir": "long",
      "conf": 0.535
    },
    "BCHUSDT": {
      "dir": "short",
      "conf": 0.761
    },
    "XMRUSDT": {
      "dir": "long",
      "conf": 0.607
    },
    "TONUSDT": {
      "dir": "long",
      "conf": 0.504
    },
    "WLFIUSDT": {
      "dir": "short",
      "conf": 0.533
    },
    "DASHUSDT": {
      "dir": "long",
      "conf": 0.546
    },
    "RAVEUSDT": {
      "dir": "long",
      "conf": 0.758
    },
    "ASTERUSDT": {
      "dir": "short",
      "conf": 0.566
    },
    "SIRENUSDT": {
      "dir": "short",
      "conf": 0.563
    },
    "1000BONKUSDT": {
      "dir": "short",
      "conf": 0.529
    },
    "APTUSDT": {
      "dir": "short",
      "conf": 0.516
    },
    "MUSDT": {
      "dir": "long",
      "conf": 0.53
    },
    "MNTUSDT": {
      "dir": "long",
      "conf": 0.504
    },
    "PENGUUSDT": {
      "dir": "long",
      "conf": 0.631
    }
  },
  "equity_hist": [
    {
      "t": "2026-04-14",
      "v": 5440.0
    },
    {
      "t": "2026-04-15",
      "v": 5409.42
    },
    {
      "t": "2026-04-16",
      "v": 5894.6
    },
    {
      "t": "2026-04-17",
      "v": 6570.21
    },
    {
      "t": "2026-04-18",
      "v": 6388.3
    },
    {
      "t": "2026-04-19",
      "v": 6256.89
    },
    {
      "t": "2026-04-20",
      "v": 5802.63
    },
    {
      "t": "2026-04-21",
      "v": 6036.57
    },
    {
      "t": "2026-04-22",
      "v": 6135.67
    },
    {
      "t": "2026-04-23",
      "v": 6157.57
    },
    {
      "t": "2026-04-24",
      "v": 7293.15
    },
    {
      "t": "2026-04-25",
      "v": 4328.2
    },
    {
      "t": "2026-04-26",
      "v": 4572.75
    },
    {
      "t": "2026-04-27",
      "v": 5182.45
    },
    {
      "t": "2026-04-28",
      "v": 5043.89
    },
    {
      "t": "2026-04-29",
      "v": 5215.1
    }
  ],
  "trade_history": [
    {
      "ts": "2026-04-29 12:22",
      "symbol": "ADAUSDT",
      "side": "Sell",
      "pnl": -3.33,
      "reason": "3/9"
    },
    {
      "ts": "2026-04-29 12:20",
      "symbol": "SOLUSDT",
      "side": "Sell",
      "pnl": 118.03,
      "reason": "2/9"
    },
    {
      "ts": "2026-04-29 12:20",
      "symbol": "SUIUSDT",
      "side": "Sell",
      "pnl": 0.81,
      "reason": "2/9"
    },
    {
      "ts": "2026-04-29 09:48",
      "symbol": "DOGEUSDT",
      "side": "Buy",
      "pnl": 3.32,
      "reason": "2/9"
    },
    {
      "ts": "2026-04-29 09:33",
      "symbol": "DOGEUSDT",
      "side": "Buy",
      "pnl": 1.47,
      "reason": "3/9"
    },
    {
      "ts": "2026-04-29 09:24",
      "symbol": "BCHUSDT",
      "side": "Buy",
      "pnl": 2.93,
      "reason": "7/9"
    },
    {
      "ts": "2026-04-29 09:08",
      "symbol": "BCHUSDT",
      "side": "Buy",
      "pnl": 14.73,
      "reason": "8/9"
    },
    {
      "ts": "2026-04-29 02:11",
      "symbol": "TAOUSDT",
      "side": "Buy",
      "pnl": 0.01,
      "reason": "마진 0.0USDT < 15"
    },
    {
      "ts": "2026-04-29 02:05",
      "symbol": "TAOUSDT",
      "side": "Buy",
      "pnl": 78.35,
      "reason": "3/9"
    },
    {
      "ts": "2026-04-29 01:49",
      "symbol": "DOTUSDT",
      "side": "Buy",
      "pnl": 0.0,
      "reason": "마진 0.0USDT < 15"
    },
    {
      "ts": "2026-04-29 01:45",
      "symbol": "ARBUSDT",
      "side": "Sell",
      "pnl": 0.8,
      "reason": "T1 진입 | GF=7 | Lv=7x | Seed=$2500(9.2%)"
    },
    {
      "ts": "2026-04-29 01:42",
      "symbol": "DOTUSDT",
      "side": "Buy",
      "pnl": 8.76,
      "reason": "3/9"
    },
    {
      "ts": "2026-04-29 01:27",
      "symbol": "DOTUSDT",
      "side": "Buy",
      "pnl": 10.6,
      "reason": "4/9"
    },
    {
      "ts": "2026-04-28 22:43",
      "symbol": "DOGEUSDT",
      "side": "Sell",
      "pnl": 6.41,
      "reason": "2/9"
    },
    {
      "ts": "2026-04-28 22:09",
      "symbol": "DOGEUSDT",
      "side": "Sell",
      "pnl": 7.07,
      "reason": "3/9"
    },
    {
      "ts": "2026-04-28 13:36",
      "symbol": "DOGEUSDT",
      "side": "Buy",
      "pnl": 7.68,
      "reason": "2/9"
    },
    {
      "ts": "2026-04-28 09:47",
      "symbol": "TAOUSDT",
      "side": "Sell",
      "pnl": -0.0,
      "reason": "마진 0.0USDT < 15"
    },
    {
      "ts": "2026-04-28 09:43",
      "symbol": "TAOUSDT",
      "side": "Sell",
      "pnl": -13.65,
      "reason": "2/9"
    },
    {
      "ts": "2026-04-28 08:17",
      "symbol": "ADAUSDT",
      "side": "Sell",
      "pnl": 1.98,
      "reason": "2/9"
    },
    {
      "ts": "2026-04-28 08:17",
      "symbol": "SUIUSDT",
      "side": "Sell",
      "pnl": 6.06,
      "reason": "2/9"
    }
  ],
  "num_days": 60
}