{
  "ts": "2026-04-14T22:20:02.128718+09:00",
  "start_date": "2026-03-01",
  "status": "running",
  "equity": 35258.33,
  "available": 33361.79,
  "unrealized": 77.06,
  "daily_pnl": -902.83,
  "total_pnl": 5258.33,
  "cum_pct": 17.53,
  "daily_avg_pct": 0.3896,
  "annual_pct": 313.41,
  "mdd": -8.02,
  "current_dd": -2.32,
  "seed_used": 1896.54,
  "seed_used_pct": 5.38,
  "long_count": 4,
  "short_count": 0,
  "positions": [
    {
      "symbol": "ADAUSDT",
      "side": "LONG",
      "pnl": -57.44,
      "pnl_pct": -0.58,
      "margin": 1246.31,
      "leverage": "8",
      "tier": "7/9",
      "entry": 0.245,
      "mark": 0.2436
    },
    {
      "symbol": "BTCUSDT",
      "side": "LONG",
      "pnl": 134.08,
      "pnl_pct": 4.59,
      "margin": 292.41,
      "leverage": "10",
      "tier": "2/9",
      "entry": 71320.7012,
      "mark": 74590.9
    },
    {
      "symbol": "LINKUSDT",
      "side": "LONG",
      "pnl": 0.41,
      "pnl_pct": 0.07,
      "margin": 88.1,
      "leverage": "7",
      "tier": "2/9",
      "entry": 9.136,
      "mark": 9.142
    },
    {
      "symbol": "AVAXUSDT",
      "side": "LONG",
      "pnl": -0.01,
      "pnl_pct": -0.88,
      "margin": 0.09,
      "leverage": "10",
      "tier": "1/10",
      "entry": 9.4692,
      "mark": 9.386
    }
  ],
  "signals": {
    "BTCUSDT": {
      "dir": "short",
      "conf": 0.551
    },
    "ETHUSDT": {
      "dir": "short",
      "conf": 0.555
    },
    "LINKUSDT": {
      "dir": "long",
      "conf": 0.589
    },
    "ADAUSDT": {
      "dir": "short",
      "conf": 0.677
    },
    "HYPEUSDT": {
      "dir": "short",
      "conf": 0.504
    },
    "1000PEPEUSDT": {
      "dir": "short",
      "conf": 0.534
    },
    "SOLUSDT": {
      "dir": "short",
      "conf": 0.681
    },
    "SUIUSDT": {
      "dir": "short",
      "conf": 0.505
    },
    "XRPUSDT": {
      "dir": "short",
      "conf": 0.585
    },
    "TAOUSDT": {
      "dir": "long",
      "conf": 0.51
    },
    "DOGEUSDT": {
      "dir": "short",
      "conf": 0.687
    },
    "HBARUSDT": {
      "dir": "short",
      "conf": 0.758
    },
    "AAVEUSDT": {
      "dir": "short",
      "conf": 0.53
    },
    "DOTUSDT": {
      "dir": "short",
      "conf": 0.539
    },
    "AVAXUSDT": {
      "dir": "long",
      "conf": 0.653
    },
    "BNBUSDT": {
      "dir": "short",
      "conf": 0.66
    },
    "TRXUSDT": {
      "dir": "long",
      "conf": 0.808
    },
    "NEARUSDT": {
      "dir": "short",
      "conf": 0.525
    },
    "ENAUSDT": {
      "dir": "short",
      "conf": 0.56
    },
    "STABLEUSDT": {
      "dir": "long",
      "conf": 0.617
    },
    "UNIUSDT": {
      "dir": "short",
      "conf": 0.596
    },
    "LTCUSDT": {
      "dir": "long",
      "conf": 0.537
    },
    "ZECUSDT": {
      "dir": "long",
      "conf": 0.502
    },
    "ARBUSDT": {
      "dir": "short",
      "conf": 0.506
    },
    "ALGOUSDT": {
      "dir": "short",
      "conf": 0.529
    },
    "TRUMPUSDT": {
      "dir": "short",
      "conf": 0.59
    },
    "WLDUSDT": {
      "dir": "long",
      "conf": 0.502
    },
    "BCHUSDT": {
      "dir": "long",
      "conf": 0.905
    },
    "XMRUSDT": {
      "dir": "short",
      "conf": 0.56
    },
    "TONUSDT": {
      "dir": "long",
      "conf": 0.504
    },
    "WLFIUSDT": {
      "dir": "short",
      "conf": 0.503
    },
    "DASHUSDT": {
      "dir": "long",
      "conf": 0.546
    },
    "RAVEUSDT": {
      "dir": "long",
      "conf": 0.788
    }
  },
  "equity_hist": [
    {
      "t": "2026-04-14",
      "v": 5258.33
    }
  ],
  "trade_history": [
    {
      "ts": "2026-04-14 22:18",
      "symbol": "AVAXUSDT",
      "side": "Buy",
      "pnl": -48.09,
      "reason": "5/10"
    },
    {
      "ts": "2026-04-14 17:16",
      "symbol": "RAVEUSDT",
      "side": "Buy",
      "pnl": 11.24,
      "reason": "2/12"
    },
    {
      "ts": "2026-04-14 17:01",
      "symbol": "RAVEUSDT",
      "side": "Buy",
      "pnl": 20.57,
      "reason": "4/12"
    },
    {
      "ts": "2026-04-14 08:38",
      "symbol": "RAVEUSDT",
      "side": "Buy",
      "pnl": -758.83,
      "reason": "L8"
    },
    {
      "ts": "2026-04-14 07:55",
      "symbol": "ETHUSDT",
      "side": "Sell",
      "pnl": -178.0,
      "reason": "External Exit"
    },
    {
      "ts": "2026-04-14 07:23",
      "symbol": "AVAXUSDT",
      "side": "Buy",
      "pnl": 0.03,
      "reason": "마진 0.1USDT < 15"
    },
    {
      "ts": "2026-04-14 07:17",
      "symbol": "AVAXUSDT",
      "side": "Buy",
      "pnl": 4.55,
      "reason": "1/10"
    },
    {
      "ts": "2026-04-14 07:16",
      "symbol": "AVAXUSDT",
      "side": "Buy",
      "pnl": 4.08,
      "reason": "-"
    },
    {
      "ts": "2026-04-14 06:57",
      "symbol": "AVAXUSDT",
      "side": "Buy",
      "pnl": 3.91,
      "reason": "2/10"
    },
    {
      "ts": "2026-04-14 04:48",
      "symbol": "LTCUSDT",
      "side": "Sell",
      "pnl": 5.93,
      "reason": "2/9"
    },
    {
      "ts": "2026-04-14 04:46",
      "symbol": "DOGEUSDT",
      "side": "Buy",
      "pnl": 32.57,
      "reason": "5/9"
    },
    {
      "ts": "2026-04-14 04:30",
      "symbol": "DOGEUSDT",
      "side": "Buy",
      "pnl": 5.17,
      "reason": "6/9"
    },
    {
      "ts": "2026-04-14 00:51",
      "symbol": "AVAXUSDT",
      "side": "Sell",
      "pnl": -0.01,
      "reason": "마진 0.1USDT < 15"
    },
    {
      "ts": "2026-04-14 00:49",
      "symbol": "AVAXUSDT",
      "side": "Sell",
      "pnl": -5.94,
      "reason": "1/9"
    },
    {
      "ts": "2026-04-13 23:30",
      "symbol": "BNBUSDT",
      "side": "Sell",
      "pnl": -14.64,
      "reason": "3/9"
    },
    {
      "ts": "2026-04-13 23:23",
      "symbol": "WLDUSDT",
      "side": "Buy",
      "pnl": 0.0,
      "reason": "마진 0.0USDT < 15"
    },
    {
      "ts": "2026-04-13 23:19",
      "symbol": "WLDUSDT",
      "side": "Buy",
      "pnl": 5.8,
      "reason": "1/11"
    },
    {
      "ts": "2026-04-13 22:51",
      "symbol": "SUIUSDT",
      "side": "Sell",
      "pnl": -1.36,
      "reason": "2/9"
    },
    {
      "ts": "2026-04-13 22:50",
      "symbol": "SUIUSDT",
      "side": "Sell",
      "pnl": -1.25,
      "reason": "2/9"
    },
    {
      "ts": "2026-04-13 22:49",
      "symbol": "DOTUSDT",
      "side": "Sell",
      "pnl": 23.78,
      "reason": "1/9"
    }
  ],
  "num_days": 45
}