{
  "ts": "2026-04-02T00:49:03.549310+09:00",
  "start_date": "2026-03-01",
  "status": "running",
  "equity": 102814.73,
  "available": 83663.2,
  "unrealized": -32.92,
  "daily_pnl": -0.15,
  "total_pnl": 10814.73,
  "cum_pct": 11.76,
  "daily_avg_pct": 0.3564,
  "annual_pct": 266.4,
  "mdd": -8.02,
  "current_dd": -0.34,
  "seed_used": 19151.53,
  "seed_used_pct": 18.63,
  "long_count": 3,
  "short_count": 9,
  "positions": [
    {
      "symbol": "TRXUSDT",
      "side": "LONG",
      "pnl": 67.07,
      "pnl_pct": 0.6,
      "margin": 1855.22,
      "leverage": "6",
      "tier": "6/9",
      "entry": 0.3133,
      "mark": 0.3152
    },
    {
      "symbol": "TRUMPUSDT",
      "side": "SHORT",
      "pnl": 79.5,
      "pnl_pct": 1.02,
      "margin": 1552.34,
      "leverage": "5",
      "tier": "9/10",
      "entry": 3.0462,
      "mark": 3.015
    },
    {
      "symbol": "ADAUSDT",
      "side": "SHORT",
      "pnl": 53.58,
      "pnl_pct": 0.38,
      "margin": 1171.34,
      "leverage": "12",
      "tier": "4/9",
      "entry": 0.2498,
      "mark": 0.2488
    },
    {
      "symbol": "BTCUSDT",
      "side": "SHORT",
      "pnl": -38.55,
      "pnl_pct": -0.46,
      "margin": 1044.55,
      "leverage": "8",
      "tier": "4/9",
      "entry": 68495.2959,
      "mark": 68811.3
    },
    {
      "symbol": "AAVEUSDT",
      "side": "SHORT",
      "pnl": 4.47,
      "pnl_pct": 0.07,
      "margin": 973.27,
      "leverage": "7",
      "tier": "4/9",
      "entry": 99.8955,
      "mark": 99.83
    },
    {
      "symbol": "SUIUSDT",
      "side": "SHORT",
      "pnl": -288.98,
      "pnl_pct": -2.12,
      "margin": 971.58,
      "leverage": "14",
      "tier": "4/9",
      "entry": 0.8804,
      "mark": 0.8991
    },
    {
      "symbol": "HBARUSDT",
      "side": "LONG",
      "pnl": -4.04,
      "pnl_pct": -0.1,
      "margin": 664.89,
      "leverage": "6",
      "tier": "3/9",
      "entry": 0.0897,
      "mark": 0.0896
    },
    {
      "symbol": "SOLUSDT",
      "side": "SHORT",
      "pnl": 0.8,
      "pnl_pct": 0.02,
      "margin": 660.6,
      "leverage": "5",
      "tier": "3/9",
      "entry": 83.6204,
      "mark": 83.6
    },
    {
      "symbol": "DOTUSDT",
      "side": "SHORT",
      "pnl": 98.3,
      "pnl_pct": 1.27,
      "margin": 553.97,
      "leverage": "14",
      "tier": "3/9",
      "entry": 1.2863,
      "mark": 1.27
    },
    {
      "symbol": "BNBUSDT",
      "side": "SHORT",
      "pnl": 16.7,
      "pnl_pct": 0.51,
      "margin": 549.24,
      "leverage": "6",
      "tier": "3/9",
      "entry": 617.1275,
      "mark": 614.0
    },
    {
      "symbol": "XRPUSDT",
      "side": "SHORT",
      "pnl": -11.66,
      "pnl_pct": -0.43,
      "margin": 385.15,
      "leverage": "7",
      "tier": "6/9",
      "entry": 1.3496,
      "mark": 1.3554
    },
    {
      "symbol": "LINKUSDT",
      "side": "LONG",
      "pnl": -10.12,
      "pnl_pct": -0.95,
      "margin": 213.84,
      "leverage": "5",
      "tier": "1/10",
      "entry": 9.084,
      "mark": 8.998
    }
  ],
  "signals": {
    "TAOUSDT": {
      "dir": "long",
      "conf": 0.509
    },
    "DOTUSDT": {
      "dir": "short",
      "conf": 0.694
    },
    "ADAUSDT": {
      "dir": "short",
      "conf": 0.783
    },
    "LINKUSDT": {
      "dir": "long",
      "conf": 0.628
    },
    "HYPEUSDT": {
      "dir": "short",
      "conf": 0.559
    },
    "BNBUSDT": {
      "dir": "short",
      "conf": 0.698
    },
    "XRPUSDT": {
      "dir": "short",
      "conf": 0.55
    },
    "NEARUSDT": {
      "dir": "short",
      "conf": 0.567
    },
    "SUIUSDT": {
      "dir": "long",
      "conf": 0.642
    },
    "1000PEPEUSDT": {
      "dir": "short",
      "conf": 0.99
    },
    "ZECUSDT": {
      "dir": "short",
      "conf": 0.54
    },
    "TRXUSDT": {
      "dir": "long",
      "conf": 0.72
    },
    "ASTERUSDT": {
      "dir": "short",
      "conf": 0.509
    },
    "TRUMPUSDT": {
      "dir": "short",
      "conf": 0.565
    },
    "1000BONKUSDT": {
      "dir": "long",
      "conf": 0.535
    },
    "SOLUSDT": {
      "dir": "short",
      "conf": 0.701
    },
    "ZROUSDT": {
      "dir": "short",
      "conf": 0.504
    },
    "WLDUSDT": {
      "dir": "short",
      "conf": 0.879
    },
    "AAVEUSDT": {
      "dir": "short",
      "conf": 0.718
    },
    "APTUSDT": {
      "dir": "short",
      "conf": 0.536
    },
    "ENAUSDT": {
      "dir": "short",
      "conf": 0.51
    },
    "TONUSDT": {
      "dir": "short",
      "conf": 0.523
    },
    "LTCUSDT": {
      "dir": "short",
      "conf": 0.724
    },
    "BCHUSDT": {
      "dir": "short",
      "conf": 0.518
    },
    "ARBUSDT": {
      "dir": "short",
      "conf": 0.526
    },
    "HBARUSDT": {
      "dir": "long",
      "conf": 0.74
    },
    "WLFIUSDT": {
      "dir": "long",
      "conf": 0.587
    },
    "BTCUSDT": {
      "dir": "short",
      "conf": 0.751
    },
    "XMRUSDT": {
      "dir": "short",
      "conf": 0.516
    },
    "FILUSDT": {
      "dir": "long",
      "conf": 0.584
    },
    "DOGEUSDT": {
      "dir": "short",
      "conf": 0.72
    },
    "ETHUSDT": {
      "dir": "short",
      "conf": 0.768
    },
    "AVAXUSDT": {
      "dir": "short",
      "conf": 0.958
    },
    "XLMUSDT": {
      "dir": "short",
      "conf": 0.563
    },
    "RENDERUSDT": {
      "dir": "long",
      "conf": 0.608
    },
    "ONDOUSDT": {
      "dir": "short",
      "conf": 0.517
    },
    "MUSDT": {
      "dir": "long",
      "conf": 0.53
    }
  },
  "equity_hist": [
    {
      "t": "2026-03-01",
      "v": 129.17
    },
    {
      "t": "2026-03-02",
      "v": -80.78
    },
    {
      "t": "2026-03-03",
      "v": 133.72
    },
    {
      "t": "2026-03-04",
      "v": 261.79
    },
    {
      "t": "2026-03-05",
      "v": 447.18
    },
    {
      "t": "2026-03-06",
      "v": 643.71
    },
    {
      "t": "2026-03-07",
      "v": 776.02
    },
    {
      "t": "2026-03-08",
      "v": 904.42
    },
    {
      "t": "2026-03-09",
      "v": 955.21
    },
    {
      "t": "2026-03-10",
      "v": 1270.09
    },
    {
      "t": "2026-03-11",
      "v": 1215.31
    },
    {
      "t": "2026-03-12",
      "v": 1407.19
    },
    {
      "t": "2026-03-13",
      "v": 1579.54
    },
    {
      "t": "2026-03-14",
      "v": 2025.6
    },
    {
      "t": "2026-03-15",
      "v": 2116.99
    },
    {
      "t": "2026-03-16",
      "v": 2106.06
    },
    {
      "t": "2026-03-17",
      "v": 2052.87
    },
    {
      "t": "2026-03-18",
      "v": 2506.66
    },
    {
      "t": "2026-03-19",
      "v": 2664.93
    },
    {
      "t": "2026-03-20",
      "v": 2864.09
    },
    {
      "t": "2026-03-21",
      "v": 2829.83
    },
    {
      "t": "2026-03-22",
      "v": 3848.84
    },
    {
      "t": "2026-03-23",
      "v": 5808.68
    },
    {
      "t": "2026-03-24",
      "v": 6731.9
    },
    {
      "t": "2026-03-25",
      "v": 9905.54
    },
    {
      "t": "2026-03-26",
      "v": 10527.72
    },
    {
      "t": "2026-03-27",
      "v": 10600.42
    },
    {
      "t": "2026-03-28",
      "v": 10630.56
    },
    {
      "t": "2026-03-29",
      "v": 10162.06
    },
    {
      "t": "2026-03-30",
      "v": 10372.08
    },
    {
      "t": "2026-03-31",
      "v": 10832.17
    },
    {
      "t": "2026-04-01",
      "v": 11707.45
    },
    {
      "t": "2026-04-02",
      "v": 11707.3
    }
  ],
  "trade_history": [
    {
      "ts": "2026-04-02 00:27",
      "symbol": "ETHUSDT",
      "side": "Buy",
      "pnl": 0.05,
      "reason": "1/9"
    },
    {
      "ts": "2026-04-02 00:20",
      "symbol": "ETHUSDT",
      "side": "Buy",
      "pnl": 0.83,
      "reason": "3/9"
    },
    {
      "ts": "2026-04-02 00:01",
      "symbol": "ETHUSDT",
      "side": "Buy",
      "pnl": -1.03,
      "reason": "4/9"
    },
    {
      "ts": "2026-04-01 23:59",
      "symbol": "1000PEPEUSDT",
      "side": "Buy",
      "pnl": 15.99,
      "reason": "2/9"
    },
    {
      "ts": "2026-04-01 23:42",
      "symbol": "1000PEPEUSDT",
      "side": "Buy",
      "pnl": 18.92,
      "reason": "3/9"
    },
    {
      "ts": "2026-04-01 21:10",
      "symbol": "ADAUSDT",
      "side": "Buy",
      "pnl": -15.33,
      "reason": "4/11"
    },
    {
      "ts": "2026-04-01 20:52",
      "symbol": "ADAUSDT",
      "side": "Buy",
      "pnl": -12.58,
      "reason": "5/11"
    },
    {
      "ts": "2026-04-01 20:49",
      "symbol": "HBARUSDT",
      "side": "Sell",
      "pnl": 14.84,
      "reason": "5/9"
    },
    {
      "ts": "2026-04-01 20:32",
      "symbol": "HBARUSDT",
      "side": "Sell",
      "pnl": 22.97,
      "reason": "6/9"
    },
    {
      "ts": "2026-04-01 17:22",
      "symbol": "DOTUSDT",
      "side": "Buy",
      "pnl": 0.0,
      "reason": "1/9"
    },
    {
      "ts": "2026-04-01 17:18",
      "symbol": "DOTUSDT",
      "side": "Buy",
      "pnl": 49.97,
      "reason": "4/9"
    },
    {
      "ts": "2026-04-01 17:13",
      "symbol": "BCHUSDT",
      "side": "Sell",
      "pnl": 9.05,
      "reason": "2/9"
    },
    {
      "ts": "2026-04-01 16:52",
      "symbol": "BCHUSDT",
      "side": "Sell",
      "pnl": 15.37,
      "reason": "3/9"
    },
    {
      "ts": "2026-04-01 15:50",
      "symbol": "ADAUSDT",
      "side": "Buy",
      "pnl": 37.72,
      "reason": "5/10"
    },
    {
      "ts": "2026-04-01 15:12",
      "symbol": "DOTUSDT",
      "side": "Buy",
      "pnl": 73.73,
      "reason": "4/9"
    },
    {
      "ts": "2026-04-01 15:08",
      "symbol": "ADAUSDT",
      "side": "Buy",
      "pnl": 32.06,
      "reason": "4/10"
    },
    {
      "ts": "2026-04-01 14:54",
      "symbol": "AAVEUSDT",
      "side": "Buy",
      "pnl": 79.6,
      "reason": "2/9"
    },
    {
      "ts": "2026-04-01 14:45",
      "symbol": "LINKUSDT",
      "side": "Buy",
      "pnl": 13.19,
      "reason": "마진 78.2USDT < 100"
    },
    {
      "ts": "2026-04-01 14:40",
      "symbol": "AAVEUSDT",
      "side": "Buy",
      "pnl": 38.57,
      "reason": "3/9"
    },
    {
      "ts": "2026-04-01 13:58",
      "symbol": "ETHUSDT",
      "side": "Buy",
      "pnl": 0.09,
      "reason": "1/9"
    }
  ],
  "num_days": 33
}